superagi/__init__.py
superagi/tools/__init__.py
superagi/tools/base_tool.py
superagi_client-1.0.1.dist-info/LICENSE
superagi_client-1.0.1.dist-info/METADATA
superagi_client-1.0.1.dist-info/WHEEL
superagi_client-1.0.1.dist-info/top_level.txt
superagi_client-1.0.1.dist-info/RECORD
