Metadata-Version: 2.1
Name: superagi-client
Version: 1.0.1
Summary: A useful module for using tools from Superagi
Author: superagi
Author-email: mukunda@superagi.com
License-File: LICENSE
Requires-Dist: pydantic
Requires-Dist: pyyaml
